tabichan/__init__.py
tabichan/__version__.py
tabichan/client.py
tabichan/main.py
tabichan/websocket_client.py
tabichan_python_sdk-0.1.0.dist-info/METADATA
tabichan_python_sdk-0.1.0.dist-info/WHEEL
tabichan_python_sdk-0.1.0.dist-info/entry_points.txt
tabichan_python_sdk-0.1.0.dist-info/licenses/LICENSE
tabichan_python_sdk-0.1.0.dist-info/RECORD
