Metadata-Version: 2.4
Name: tabichan-python-sdk
Version: 0.1.0
Summary: PodTech's Tabichan API SDK
Project-URL: Homepage, https://github.com/Podtech-AI/tabichan-python-sdk
Project-URL: Repository, https://github.com/Podtech-AI/tabichan-python-sdk
Project-URL: Issues, https://github.com/Podtech-AI/tabichan-python-sdk/issues
Author-email: Maxence Leguéry <maxence@podtech.tech>
License-File: LICENSE
Classifier: Development Status :: 3 - Alpha
Classifier: Intended Audience :: Developers
Classifier: License :: OSI Approved :: MIT License
Classifier: Programming Language :: Python :: 3
Classifier: Programming Language :: Python :: 3.12
Requires-Python: >=3.9
Requires-Dist: requests>=2.32.4
Requires-Dist: websockets>=13.0
